psychoscope/__init__.py
psychoscope/main.py
psychoscope-0.0.1.dist-info/METADATA
psychoscope-0.0.1.dist-info/WHEEL
psychoscope-0.0.1.dist-info/licenses/LICENSE
psychoscope-0.0.1.dist-info/RECORD
